mm_game/__init__.py
mm_game/_core.cp310-win_amd64.pyd
mm_game-0.0.4.dist-info/METADATA
mm_game-0.0.4.dist-info/WHEEL
mm_game-0.0.4.dist-info/licenses/LICENSE
mm_game-0.0.4.dist-info/RECORD
